lp2name/__init__.py
lp2name/models.py
lp2name-0.2.4.dist-info/LICENSE
lp2name-0.2.4.dist-info/METADATA
lp2name-0.2.4.dist-info/WHEEL
lp2name-0.2.4.dist-info/top_level.txt
lp2name-0.2.4.dist-info/RECORD
