Metadata-Version: 2.1
Name: lp2name
Version: 0.2.4
Summary: Minecraft LuckPerms API
Home-page: https://git.cofob.ru/cofob/lp2name
License: UNKNOWN
Platform: UNKNOWN
Requires-Python: >=3.6
License-File: LICENSE
Requires-Dist: mysql-connector-python
